pheweb/__init__.py
pheweb/command_line.py
pheweb/conf.py
pheweb/conf_utils.py
pheweb/file_utils.py
pheweb/parse_utils.py
pheweb/utils.py
pheweb/version.py
pheweb/weetabix.py
pheweb/load/__init__.py
pheweb/load/add_genes.py
pheweb/load/add_rsids.py
pheweb/load/augment_phenos.py
pheweb/load/best_of_pheno.py
pheweb/load/bgzip_phenos.py
pheweb/load/cluster.py
pheweb/load/detect_ref.py
pheweb/load/download_genes.py
pheweb/load/download_genes_from_scratch.py
pheweb/load/download_rsids.py
pheweb/load/download_rsids_from_scratch.py
pheweb/load/gather_pvalues_for_each_gene.py
pheweb/load/load_utils.py
pheweb/load/make_cpras_rsids_sqlite3.py
pheweb/load/make_gene_aliases_sqlite3.py
pheweb/load/make_gene_aliases_trie.py
pheweb/load/make_tries.py
pheweb/load/manhattan.py
pheweb/load/matrix.py
pheweb/load/parse_input_files.py
pheweb/load/pheno_correlation.py
pheweb/load/phenotypes.py
pheweb/load/process_assoc_files.py
pheweb/load/qq.py
pheweb/load/read_input_file.py
pheweb/load/sites.py
pheweb/load/slurm-parse.py
pheweb/load/top_hits.py
pheweb/load/top_loci.py
pheweb/load/wsgi.py
pheweb/load/cffi/_x.abi3.so
pheweb/load/cffi/ffibuilder.py
pheweb/load/cffi/x.cpp
pheweb/load/phenolist/__init__.py
pheweb/serve/__init__.py
pheweb/serve/auth.py
pheweb/serve/autocomplete.py
pheweb/serve/run.py
pheweb/serve/server.py
pheweb/serve/server_utils.py
pheweb/serve/static/common.css
pheweb/serve/static/common.js
pheweb/serve/static/gene.js
pheweb/serve/static/pheno-filter.js
pheweb/serve/static/pheno.js
pheweb/serve/static/phenotypes.js
pheweb/serve/static/region.css
pheweb/serve/static/region.js
pheweb/serve/static/top_hits.js
pheweb/serve/static/variant.js
pheweb/serve/static/fonts/glyphicons-halflings-regular.svg
pheweb/serve/static/fonts/glyphicons-halflings-regular.ttf
pheweb/serve/static/fonts/glyphicons-halflings-regular.woff
pheweb/serve/static/fonts/glyphicons-halflings-regular.woff2
pheweb/serve/static/vendor/stream_table-1.1.1.min.js
pheweb/serve/templates/#pheno.html#
PheWeb-1.3.15.dist-info/LICENSE
PheWeb-1.3.15.dist-info/METADATA
PheWeb-1.3.15.dist-info/WHEEL
PheWeb-1.3.15.dist-info/entry_points.txt
PheWeb-1.3.15.dist-info/top_level.txt
PheWeb-1.3.15.dist-info/RECORD
